pandas_toolkit/__init__.py
pandas_toolkit/_version.py
pandas_toolkit/ml/__init__.py
pandas_toolkit/ml/tests/__init__.py
pandas_toolkit/ml/tests/test_ml.py
pandas_toolkit/nn/Model.py
pandas_toolkit/nn/__init__.py
pandas_toolkit/nn/tests/__init__.py
pandas_toolkit/nn/tests/test_nn.py
pandas_toolkit/utils/__init__.py
pandas_toolkit/utils/custom_types.py
pandas_toolkit-0.1.3.dist-info/LICENSE
pandas_toolkit-0.1.3.dist-info/METADATA
pandas_toolkit-0.1.3.dist-info/WHEEL
pandas_toolkit-0.1.3.dist-info/top_level.txt
pandas_toolkit-0.1.3.dist-info/RECORD
